glue_biscuit/__init__.py
glue_biscuit/conftest.py
glue_biscuit/job_argument_utils.py
glue_biscuit/merge_utils.py
glue_biscuit/schema_utils.py
glue_biscuit/test/__init__.py
glue_biscuit/test/data_frame_matcher.py
glue_biscuit/test/dynamic_frame_matcher.py
glue_biscuit/test/fixtures.py
glue_biscuit/test_job_argument_utils.py
glue_biscuit/test_merge_utils.py
glue_biscuit/test_schema_utils.py
glue_biscuit-0.0.2.dist-info/METADATA
glue_biscuit-0.0.2.dist-info/WHEEL
glue_biscuit-0.0.2.dist-info/RECORD
